{
  "resourceType": "CodeSystem",
  "url": "http://ga4gh.org/fhir/phenopackets/CodeSystem/document-type",
  "version": "1.0.0",
  "name": "DocumentType",
  "status": "active",
  "experimental": false,
  "publisher": "GA4GH",
  "description": "Represents the different types of documents in the Phenopackets standard.",
  "caseSensitive": false,
  "valueSet": "http://ga4gh.org/fhir/phenopackets/CodeSystem/document-type?vs",
  "title": "Document Type",
  "content": "complete",
  "concept": [
    {
      "code": "phenopacket",
      "display": "Phenopacket",
      "definition": "Phenopacket"
    },
    {
      "code": "family",
      "display": "Family",
      "definition": "Family"
    },
    {
      "code": "cohort",
      "display": "Cohort",
      "definition": "Cohort"
    },
    {
      "code": "cancer-packet",
      "display": "Cancer packet",
      "definition": "Cancer packet"
    }
  ]
}