<?xml version="1.0" encoding="utf-8"?>
<StructureDefinition xmlns="http://hl7.org/fhir">
  <url value="http://ga4gh.org/fhir/phenopackets/StructureDefinition/Cohort" />
  <version value="1.0.0" />
  <name value="Cohort" />
  <status value="draft" />
  <fhirVersion value="4.0.0" />
  <kind value="resource" />
  <abstract value="false" />
  <type value="Composition" />
  <baseDefinition value="http://hl7.org/fhir/StructureDefinition/Composition" />
  <derivation value="constraint" />
  <differential>
    <element id="Composition.type.coding.system">
      <path value="Composition.type.coding.system" />
      <fixedUri value="http://ga4gh.org/fhir/phenopackets/CodeSystem/document-type" />
    </element>
    <element id="Composition.type.coding.code">
      <path value="Composition.type.coding.code" />
      <fixedCode value="cohort" />
    </element>
    <element id="Composition.subject">
      <path value="Composition.subject" />
      <max value="0" />
    </element>
    <element id="Composition.encounter">
      <path value="Composition.encounter" />
      <max value="0" />
    </element>
    <element id="Composition.title">
      <path value="Composition.title" />
      <fixedString value="Cohort" />
    </element>
    <element id="Composition.confidentiality">
      <path value="Composition.confidentiality" />
      <max value="0" />
    </element>
    <element id="Composition.attester">
      <path value="Composition.attester" />
      <max value="0" />
    </element>
    <element id="Composition.custodian">
      <path value="Composition.custodian" />
      <max value="0" />
    </element>
    <element id="Composition.relatesTo">
      <path value="Composition.relatesTo" />
      <max value="0" />
    </element>
    <element id="Composition.event">
      <path value="Composition.event" />
      <max value="0" />
    </element>
    <element id="Composition.section">
      <path value="Composition.section" />
      <slicing>
        <discriminator>
          <type value="value" />
          <path value="code" />
        </discriminator>
        <rules value="open" />
      </slicing>
    </element>
    <element id="Composition.section:members">
      <path value="Composition.section" />
      <sliceName value="members" />
      <sliceIsConstraining value="false" />
    </element>
    <element id="Composition.section:members.title">
      <path value="Composition.section.title" />
      <short value="Members" />
      <definition value="One Phenopacket is included for each member of the cohort." />
      <fixedString value="Members" />
    </element>
    <element id="Composition.section:members.author">
      <path value="Composition.section.author" />
      <max value="0" />
    </element>
    <element id="Composition.section:members.focus">
      <path value="Composition.section.focus" />
      <max value="0" />
    </element>
    <element id="Composition.section:members.text">
      <path value="Composition.section.text" />
      <max value="0" />
    </element>
    <element id="Composition.section:members.mode">
      <path value="Composition.section.mode" />
      <fixedCode value="snapshot" />
    </element>
    <element id="Composition.section:members.orderedBy">
      <path value="Composition.section.orderedBy" />
      <max value="0" />
    </element>
    <element id="Composition.section:members.entry">
      <path value="Composition.section.entry" />
      <short value="One Phenopacket is included for each member of the cohort." />
      <type>
        <code value="Reference" />
        <targetProfile value="http://ga4gh.org/fhir/phenopackets/StructureDefinition/Phenopacket" />
        <aggregation value="bundled" />
      </type>
    </element>
    <element id="Composition.section:proband.emptyReason">
      <path value="Composition.section.emptyReason" />
      <max value="0" />
    </element>
    <element id="Composition.section:phenotypes.section">
      <path value="Composition.section.section" />
      <max value="0" />
    </element>
  </differential>
</StructureDefinition>